<?xml version="1.0" encoding="UTF-8"?>
<ROM>
  <RomName>HydrogenOS</RomName> <!-- Название прошивки -->
  <VersionName>Open_HARDGEYNER_Beta_7</VersionName> <!-- Версия прошивки и её название при скачивании, без пробелов -->
  <VersionNumber type="integer">20200118</VersionNumber> <!-- Версия прошивки для ota, в новой версии ставить версию больше 20160203 -->
  <DirectUrl>https://mirrors.lolinet.com/firmware/gsi/HydrogenOS/HydrogenOS-AB-9-20190614-ErfanGSI.img.7z</DirectUrl> <!-- Прямая ссылка на файл, для скачивания, лучше использовать прямую -->
  <HttpUrl>https://mirrors.lolinet.com/firmware/gsi/HydrogenOS/HydrogenOS-AB-9-20190614-ErfanGSI.img.7z</HttpUrl> <!-- Ссылка на файл, для скачивания через браузер, лучше использовать прямую -->
  <Android>10</Android> <!-- Версия android, смотреть в buld.prop или настройках прошивки -->
  <CheckMD5>B9348A979F5D6F495D2BC9442F81B1F7</CheckMD5> <!-- Контрольный md5 размер файла, для сравнения, полноценности скачаного файла -->
  <FileSize type="integer">1958060886</FileSize>  <!-- Размер скачиваемого файла, в байтах -->
  <Developer>HADGEYNER</Developer> <!-- Ник, имя разработчика'ов -->
  <AddonCount>1</AddonCount>
  <AddonCount>2</AddonCount>
  <AddonCount>3</AddonCount>
  <AddonCount>4</AddonCount>
  <AddonCount>5</AddonCount>
  <AddonCount>6</AddonCount>
  <AddonCount>7</AddonCount>
  <AddonCount>8</AddonCount>
  <AddonsURL>https://raw.githubusercontent.com/Nervnyi1990/lite-aex-ota/master/addons.xml</AddonsURL>
  <WebsiteURL>https://vk.com/i_feel_art</WebsiteURL>
  <DonateURL>https://money.yandex.ru/to/410012966283463</DonateURL> <!-- Ссылка для установки реквезитов для пожертвований -->
  <Changelog>
  ** Port version 1.0.1
    
  *  Сконвертировал Требл прошивку
    
     Converted Treble rom
    
  *  Портировал Требл прошивку
    
     Ported Treble rom
    
  *  Добавлен Русский перевод (около 15к строк) 
    
     Russian translation added (about 15к lines)
    
  *  Починил звук 
    
     Sound fix
    
  *  Исправленна яркость/автояркость
    
     Fix brightness
    
  *  Исправленны графические баги 
    
     Fixed Graphic bugs
    
  *  Исправленны рандобные перезагрузки
    
     Fixed random reboot
    
  *  Исправленны графические темы
        
    Fixed graphic themes
    
  </Changelog> <!-- Список изменений, новой версии прошивки, пишем что нужно -->
</ROM>
